Metadata-Version: 1.2
Name: simple-salesforce-2-7
Version: 1.0.6
Summary: A fork of Simiple Salesforce that runs on Python 2.7.
Home-page: https://github.com/taulia/simple-salesforce-2-7
Author: Nick Catalano
Author-email: nickcatal@gmail.com
Maintainer: Brady Cale
Maintainer-email: wbcale@gmail.com
License: Apache 2.0
Keywords: python salesforce salesforce.com
Platform: UNKNOWN
Classifier: Development Status :: 5 - Production/Stable
Classifier: License :: OSI Approved :: Apache Software License
Classifier: Intended Audience :: Developers
Classifier: Intended Audience :: System Administrators
Classifier: Operating System :: OS Independent
Classifier: Topic :: Internet :: WWW/HTTP
Classifier: Programming Language :: Python :: 2.7
